[{"id":1,"first_name":"Markos","last_name":"Hutchinges","mobile":"532-922-5816","email":"mhutchinges0@google.com.au"},
{"id":2,"first_name":"Sawyere","last_name":"Osgood","mobile":"804-836-3042","email":"sosgood1@wunderground.com"},
{"id":3,"first_name":"Estell","last_name":"Hatterslay","mobile":"530-370-3948","email":"ehatterslay2@angelfire.com"},
{"id":4,"first_name":"Derril","last_name":"Lepick","mobile":"760-579-5351","email":"dlepick3@lulu.com"},
{"id":5,"first_name":"Jill","last_name":"De Cristoforo","mobile":"271-349-7439","email":"jdecristoforo4@elegantthemes.com"},
{"id":6,"first_name":"Mose","last_name":"O' Brian","mobile":"829-281-7414","email":"mobrian5@sbwire.com"},
{"id":7,"first_name":"Samuele","last_name":"Metterick","mobile":"776-776-4797","email":"smetterick6@ox.ac.uk"},
{"id":8,"first_name":"Lida","last_name":"Drinkwater","mobile":"333-580-2613","email":"ldrinkwater7@vistaprint.com"},
{"id":9,"first_name":"Sula","last_name":"McMeeking","mobile":"616-275-3674","email":"smcmeeking8@chron.com"},
{"id":10,"first_name":"Willis","last_name":"Wixey","mobile":"242-505-2401","email":"wwixey9@cloudflare.com"},
{"id":11,"first_name":"Rudolf","last_name":"Donnan","mobile":"502-376-4204","email":"rdonnana@php.net"},
{"id":12,"first_name":"Jasen","last_name":"Mertel","mobile":"377-878-0814","email":"jmertelb@timesonline.co.uk"},
{"id":13,"first_name":"Demetria","last_name":"Chadbourne","mobile":"257-285-7280","email":"dchadbournec@nih.gov"},
{"id":14,"first_name":"Everard","last_name":"Courtonne","mobile":"654-318-3202","email":"ecourtonned@china.com.cn"},
{"id":15,"first_name":"Frasquito","last_name":"Horsted","mobile":"282-300-5395","email":"fhorstede@aol.com"},
{"id":16,"first_name":"Jefferey","last_name":"Durden","mobile":"288-463-7052","email":"jdurdenf@prlog.org"},
{"id":17,"first_name":"Kasper","last_name":"Corteis","mobile":"358-164-4596","email":"kcorteisg@friendfeed.com"},
{"id":18,"first_name":"Luella","last_name":"Grigoliis","mobile":"937-904-4495","email":"lgrigoliish@51.la"},
{"id":19,"first_name":"Sam","last_name":"Grimsell","mobile":"545-628-3338","email":"sgrimselli@ftc.gov"},
{"id":20,"first_name":"Gena","last_name":"Robbel","mobile":"951-907-1258","email":"grobbelj@dedecms.com"},
{"id":21,"first_name":"Enrique","last_name":"Frigout","mobile":"393-696-5672","email":"efrigoutk@skyrock.com"},
{"id":22,"first_name":"Phelia","last_name":"Hanks","mobile":"956-202-6173","email":"phanksl@simplemachines.org"},
{"id":23,"first_name":"Dale","last_name":"Beckmann","mobile":"519-612-0837","email":"dbeckmannm@mit.edu"},
{"id":24,"first_name":"Hyacinth","last_name":"Tofts","mobile":"349-533-4021","email":"htoftsn@flavors.me"},
{"id":25,"first_name":"Minnie","last_name":"Brunon","mobile":"549-470-5230","email":"mbrunono@cam.ac.uk"},
{"id":26,"first_name":"Bessie","last_name":"Mateu","mobile":"712-207-6959","email":"bmateup@gravatar.com"},
{"id":27,"first_name":"Timothee","last_name":"Boltwood","mobile":"694-908-3918","email":"tboltwoodq@theguardian.com"},
{"id":28,"first_name":"Susanetta","last_name":"Kubas","mobile":"193-833-7500","email":"skubasr@fotki.com"},
{"id":29,"first_name":"Aveline","last_name":"Landeaux","mobile":"187-804-1122","email":"alandeauxs@cargocollective.com"},
{"id":30,"first_name":"Jerrylee","last_name":"Brennon","mobile":"190-785-8708","email":"jbrennont@dion.ne.jp"},
{"id":31,"first_name":"Reece","last_name":"Yurevich","mobile":"824-328-3087","email":"ryurevichu@tmall.com"},
{"id":32,"first_name":"Jerrilee","last_name":"Abrahamsohn","mobile":"472-914-9167","email":"jabrahamsohnv@xing.com"},
{"id":33,"first_name":"Cody","last_name":"Faherty","mobile":"927-202-7641","email":"cfahertyw@addtoany.com"},
{"id":34,"first_name":"Allison","last_name":"Atchly","mobile":"133-767-9072","email":"aatchlyx@mozilla.com"},
{"id":35,"first_name":"Ugo","last_name":"Gilardoni","mobile":"821-882-7225","email":"ugilardoniy@yelp.com"},
{"id":36,"first_name":"Janot","last_name":"Klessmann","mobile":"765-231-2676","email":"jklessmannz@theglobeandmail.com"},
{"id":37,"first_name":"Kimberley","last_name":"Gravells","mobile":"305-497-9142","email":"kgravells10@omniture.com"},
{"id":38,"first_name":"Ikey","last_name":"Anthiftle","mobile":"830-538-1642","email":"ianthiftle11@globo.com"},
{"id":39,"first_name":"Celestia","last_name":"Althrope","mobile":"266-245-9276","email":"calthrope12@nsw.gov.au"},
{"id":40,"first_name":"Isabel","last_name":"Zanneli","mobile":"788-214-5066","email":"izanneli13@pbs.org"},
{"id":41,"first_name":"Livy","last_name":"Scone","mobile":"960-927-1420","email":"lscone14@tiny.cc"},
{"id":42,"first_name":"Marshall","last_name":"Weekley","mobile":"994-863-2185","email":"mweekley15@washingtonpost.com"},
{"id":43,"first_name":"Rory","last_name":"Theobalds","mobile":"538-378-2896","email":"rtheobalds16@mapquest.com"},
{"id":44,"first_name":"Tuck","last_name":"Pizer","mobile":"902-275-9823","email":"tpizer17@sun.com"},
{"id":45,"first_name":"Shalna","last_name":"Cranson","mobile":"718-134-4710","email":"scranson18@tmall.com"},
{"id":46,"first_name":"Giselbert","last_name":"Devereu","mobile":"367-556-5959","email":"gdevereu19@weather.com"},
{"id":47,"first_name":"Marjie","last_name":"Rushmere","mobile":"596-962-7291","email":"mrushmere1a@vistaprint.com"},
{"id":48,"first_name":"Guthrie","last_name":"Hardiker","mobile":"317-938-1399","email":"ghardiker1b@wix.com"},
{"id":49,"first_name":"Reagen","last_name":"Pasque","mobile":"587-785-8599","email":"rpasque1c@123-reg.co.uk"},
{"id":50,"first_name":"Vergil","last_name":"O'Garmen","mobile":"426-727-7945","email":"vogarmen1d@edublogs.org"},
{"id":51,"first_name":"Constantino","last_name":"Columbell","mobile":"753-226-1721","email":"ccolumbell1e@phoca.cz"},
{"id":52,"first_name":"Kliment","last_name":"Hubbins","mobile":"622-113-1266","email":"khubbins1f@123-reg.co.uk"},
{"id":53,"first_name":"Yank","last_name":"Langelaan","mobile":"707-431-1546","email":"ylangelaan1g@dailymotion.com"},
{"id":54,"first_name":"Meggy","last_name":"Plom","mobile":"635-180-3427","email":"mplom1h@squarespace.com"},
{"id":55,"first_name":"Elihu","last_name":"Innett","mobile":"385-925-5352","email":"einnett1i@surveymonkey.com"},
{"id":56,"first_name":"Jedd","last_name":"Niland","mobile":"144-169-2391","email":"jniland1j@macromedia.com"},
{"id":57,"first_name":"Dall","last_name":"Cornford","mobile":"519-981-1978","email":"dcornford1k@chicagotribune.com"},
{"id":58,"first_name":"Ferdinande","last_name":"Fogarty","mobile":"253-956-8609","email":"ffogarty1l@cbsnews.com"},
{"id":59,"first_name":"Rheba","last_name":"Gerrelts","mobile":"550-806-4669","email":"rgerrelts1m@ucsd.edu"},
{"id":60,"first_name":"Yurik","last_name":"Dudney","mobile":"621-631-5901","email":"ydudney1n@rakuten.co.jp"},
{"id":61,"first_name":"Culver","last_name":"Casina","mobile":"986-843-6097","email":"ccasina1o@indiatimes.com"},
{"id":62,"first_name":"Georges","last_name":"Fitt","mobile":"525-114-8121","email":"gfitt1p@flavors.me"},
{"id":63,"first_name":"Myca","last_name":"Libreros","mobile":"630-700-5071","email":"mlibreros1q@weibo.com"},
{"id":64,"first_name":"Andrei","last_name":"Cant","mobile":"833-764-7345","email":"acant1r@admin.ch"},
{"id":65,"first_name":"Jilly","last_name":"Rumsey","mobile":"935-161-7467","email":"jrumsey1s@accuweather.com"},
{"id":66,"first_name":"Delmer","last_name":"Bottom","mobile":"733-776-0088","email":"dbottom1t@xinhuanet.com"},
{"id":67,"first_name":"Noel","last_name":"Monketon","mobile":"396-339-4217","email":"nmonketon1u@facebook.com"},
{"id":68,"first_name":"Euell","last_name":"Buzza","mobile":"904-851-7575","email":"ebuzza1v@reverbnation.com"},
{"id":69,"first_name":"Bondie","last_name":"Harral","mobile":"432-239-6023","email":"bharral1w@constantcontact.com"},
{"id":70,"first_name":"Noelani","last_name":"Domingues","mobile":"449-192-3183","email":"ndomingues1x@technorati.com"},
{"id":71,"first_name":"Tatiania","last_name":"Tring","mobile":"598-704-4252","email":"ttring1y@fotki.com"},
{"id":72,"first_name":"Peg","last_name":"Moodie","mobile":"467-720-1426","email":"pmoodie1z@histats.com"},
{"id":73,"first_name":"Jennie","last_name":"Ledwich","mobile":"217-329-3919","email":"jledwich20@cyberchimps.com"},
{"id":74,"first_name":"Clare","last_name":"Lindenboim","mobile":"418-929-6856","email":"clindenboim21@apache.org"},
{"id":75,"first_name":"Joey","last_name":"Westwood","mobile":"710-580-7838","email":"jwestwood22@uol.com.br"},
{"id":76,"first_name":"Christian","last_name":"Bucksey","mobile":"200-985-5657","email":"cbucksey23@hp.com"},
{"id":77,"first_name":"Gratia","last_name":"Dikle","mobile":"812-643-4804","email":"gdikle24@netlog.com"},
{"id":78,"first_name":"Pattie","last_name":"Tersay","mobile":"640-368-0316","email":"ptersay25@si.edu"},
{"id":79,"first_name":"Grace","last_name":"Pheazey","mobile":"646-875-7809","email":"gpheazey26@sitemeter.com"},
{"id":80,"first_name":"Madonna","last_name":"Crewes","mobile":"521-208-4185","email":"mcrewes27@mozilla.com"},
{"id":81,"first_name":"Arleyne","last_name":"Brewer","mobile":"582-875-8890","email":"abrewer28@disqus.com"},
{"id":82,"first_name":"Suzie","last_name":"Kitcher","mobile":"602-892-8905","email":"skitcher29@cocolog-nifty.com"},
{"id":83,"first_name":"Arnuad","last_name":"McGahern","mobile":"439-325-7557","email":"amcgahern2a@unesco.org"},
{"id":84,"first_name":"Karalynn","last_name":"Jesper","mobile":"513-885-7863","email":"kjesper2b@privacy.gov.au"},
{"id":85,"first_name":"Aube","last_name":"Tongs","mobile":"762-259-2845","email":"atongs2c@howstuffworks.com"},
{"id":86,"first_name":"Octavius","last_name":"Rielly","mobile":"621-420-4496","email":"orielly2d@etsy.com"},
{"id":87,"first_name":"Juana","last_name":"Tooher","mobile":"323-944-5344","email":"jtooher2e@wp.com"},
{"id":88,"first_name":"Weidar","last_name":"Georgievski","mobile":"549-949-7681","email":"wgeorgievski2f@ycombinator.com"},
{"id":89,"first_name":"Jess","last_name":"Brickham","mobile":"264-725-2491","email":"jbrickham2g@delicious.com"},
{"id":90,"first_name":"Annamaria","last_name":"Stroobant","mobile":"180-923-3048","email":"astroobant2h@telegraph.co.uk"},
{"id":91,"first_name":"Elizabeth","last_name":"Bemrose","mobile":"925-140-6562","email":"ebemrose2i@twitpic.com"},
{"id":92,"first_name":"Taffy","last_name":"Isaksen","mobile":"338-146-4182","email":"tisaksen2j@disqus.com"},
{"id":93,"first_name":"Portie","last_name":"Flag","mobile":"996-251-7090","email":"pflag2k@vkontakte.ru"},
{"id":94,"first_name":"Bertrand","last_name":"Morey","mobile":"417-415-9284","email":"bmorey2l@printfriendly.com"},
{"id":95,"first_name":"Natala","last_name":"Jacquemot","mobile":"259-852-6977","email":"njacquemot2m@sun.com"},
{"id":96,"first_name":"Guenevere","last_name":"Janaway","mobile":"185-390-6752","email":"gjanaway2n@shop-pro.jp"},
{"id":97,"first_name":"Alaric","last_name":"Laird","mobile":"199-657-6170","email":"alaird2o@yahoo.co.jp"},
{"id":98,"first_name":"Allie","last_name":"Sever","mobile":"992-358-0856","email":"asever2p@pbs.org"},
{"id":99,"first_name":"Godard","last_name":"Grabb","mobile":"487-647-9551","email":"ggrabb2q@dell.com"},
{"id":100,"first_name":"Corly","last_name":"Kinahan","mobile":"690-943-1662","email":"ckinahan2r@webeden.co.uk"}]